<?xml version="1.0" encoding="utf-8"?>
<extension version="2.5" type="plugin" group="system" method="upgrade">
	<name>PLG_SYSTEM_ASSIGNMENTPREVIEWS_NAME</name>
	<author>Alejandro Löwy</author>
	<creationDate>01.06.2018</creationDate>
	<copyright>Copyright (C) 2018 Regiosites. All rights reserved.</copyright>
	<license>http://www.gnu.org/licenses/gpl-2.0.html</license>
	<authorEmail>info@w3smart-tools.com</authorEmail>
	<authorUrl>https://w3smart-tools.comr</authorUrl>
	<version>1.0</version>
	<scriptfile>install.php</scriptfile>
	<description>PLG_SYSTEM_ASSIGNMENTPREVIEWS_DESCRIPTION</description>
	<languages folder="language">
		<language tag="en-GB">en-GB/en-GB.plg_system_assignedpreview.ini</language>
		<language tag="en-GB">en-GB/en-GB.plg_system_assignedpreview.sys.ini</language>
	</languages>
	<updateservers>
	</updateservers>
	<files>
		<filename plugin="assignmentpreviews">assignmentpreviews.php</filename>
		<filename>index.html</filename>
		<filename>LICENSE.txt</filename>
		<folder>form</folder>
		<folder>field</folder>
	</files>
</extension>
